jupyterlab_celltests/__init__.py
jupyterlab_celltests/_version.py
jupyterlab_celltests/define.py
jupyterlab_celltests/extension.py
jupyterlab_celltests/lint.py
jupyterlab_celltests/shared.py
jupyterlab_celltests/test.py
jupyterlab_celltests/tests_vendored.py
jupyterlab_celltests/tests/__init__.py
jupyterlab_celltests/tests/basic.ipynb
jupyterlab_celltests/tests/magics.ipynb
jupyterlab_celltests/tests/more.ipynb
jupyterlab_celltests/tests/test_all.py
jupyterlab_celltests/tests/test_extension.py
jupyterlab_celltests/tests/test_init.py
jupyterlab_celltests/tests/test_lint.py
jupyterlab_celltests/tests/test_shared.py
jupyterlab_celltests/tests/test_tests.py
jupyterlab_celltests/tests/js/activate.test.ts
jupyterlab_celltests/tests/js/assetsTransformer.js
jupyterlab_celltests/tests/js/export.test.ts
jupyterlab_celltests/tests/js/fileMock.js
jupyterlab_celltests/tests/js/styleMock.js
jupyterlab_celltests-0.1.3.data/data/etc/jupyter/jupyter_notebook_config.d/jupyterlab_celltests.json
jupyterlab_celltests-0.1.3.data/data/share/jupyter/lab/extensions/jupyterlab_celltests-0.1.3.tgz
jupyterlab_celltests-0.1.3.dist-info/LICENSE
jupyterlab_celltests-0.1.3.dist-info/METADATA
jupyterlab_celltests-0.1.3.dist-info/WHEEL
jupyterlab_celltests-0.1.3.dist-info/top_level.txt
jupyterlab_celltests-0.1.3.dist-info/RECORD
