Metadata-Version: 2.1
Name: jupyterlab-celltests
Version: 0.1.3
Summary: Cell-by-cell tests for JupyterLab
Home-page: https://github.com/timkpaine/jupyterlab_celltests
Author: Tim Paine
Author-email: t.paine154@gmail.com
License: Apache 2.0
Keywords: jupyter jupyterlab
Platform: UNKNOWN
Classifier: Development Status :: 3 - Alpha
Classifier: Programming Language :: Python :: 3
Classifier: Programming Language :: Python :: 3.6
Classifier: Programming Language :: Python :: 3.7
Classifier: Programming Language :: Python :: 3.8
Classifier: Framework :: Jupyter
Requires-Dist: jupyterlab (>=1.0.0)
Requires-Dist: nbval (>=0.9.1)
Requires-Dist: nbconvert
Requires-Dist: pytest (>=4.4.0)
Requires-Dist: pytest-html (>=1.20.0)
Requires-Dist: flake8
Provides-Extra: dev
Requires-Dist: bump2version ; extra == 'dev'
Requires-Dist: autopep8 ; extra == 'dev'
Requires-Dist: pytest-cov (>=2.6.1) ; extra == 'dev'
Requires-Dist: mock ; extra == 'dev'
